cyberrangecz/topology_definition/__init__.py
cyberrangecz/topology_definition/image_naming.py
cyberrangecz/topology_definition/models.py
cyberrangecz/topology_definition/utils.py
cyberrangecz/topology_definition/validators.py
cyberrangecz_topology_definition-0.5.11.dist-info/LICENSE
cyberrangecz_topology_definition-0.5.11.dist-info/METADATA
cyberrangecz_topology_definition-0.5.11.dist-info/WHEEL
cyberrangecz_topology_definition-0.5.11.dist-info/top_level.txt
cyberrangecz_topology_definition-0.5.11.dist-info/RECORD
