Metadata-Version: 2.1
Name: cyberrangecz-topology-definition
Version: 0.5.11
Summary: topology-definition
Author: cybersecurityhub.cz
Requires-Python: >=3
License-File: LICENSE
Requires-Dist: yamlize>=0.6
Requires-Dist: structlog>=19.2
Requires-Dist: netaddr>=0.7
